[
  {
    "lat": 48.467977,
    "lon": -121.058616
  },
  {
    "lat": 48.468153,
    "lon": -121.058278
  },
  {
    "lat": 48.468017,
    "lon": -121.057146
  },
  {
    "lat": 48.468166,
    "lon": -121.055091
  },
  {
    "lat": 48.46804,
    "lon": -121.054394
  },
  {
    "lat": 48.468738,
    "lon": -121.055646
  },
  {
    "lat": 48.468751,
    "lon": -121.05643
  },
  {
    "lat": 48.469189,
    "lon": -121.055634
  },
  {
    "lat": 48.469442,
    "lon": -121.056072
  },
  {
    "lat": 48.469707,
    "lon": -121.055324
  },
  {
    "lat": 48.469793,
    "lon": -121.055533
  },
  {
    "lat": 48.469901,
    "lon": -121.054696
  },
  {
    "lat": 48.469789,
    "lon": -121.054218
  },
  {
    "lat": 48.469982,
    "lon": -121.054286
  },
  {
    "lat": 48.469707,
    "lon": -121.052918
  },
  {
    "lat": 48.469977,
    "lon": -121.053323
  },
  {
    "lat": 48.469863,
    "lon": -121.052362
  },
  {
    "lat": 48.470472,
    "lon": -121.051701
  },
  {
    "lat": 48.470734,
    "lon": -121.052017
  },
  {
    "lat": 48.47127,
    "lon": -121.05204
  },
  {
    "lat": 48.471706,
    "lon": -121.052572
  },
  {
    "lat": 48.472917,
    "lon": -121.054559
  },
  {
    "lat": 48.473148,
    "lon": -121.055207
  },
  {
    "lat": 48.473506,
    "lon": -121.055508
  },
  {
    "lat": 48.473673,
    "lon": -121.056315
  },
  {
    "lat": 48.473903,
    "lon": -121.05619
  },
  {
    "lat": 48.474012,
    "lon": -121.057166
  },
  {
    "lat": 48.474316,
    "lon": -121.057167
  },
  {
    "lat": 48.474451,
    "lon": -121.0574
  },
  {
    "lat": 48.474632,
    "lon": -121.057408
  },
  {
    "lat": 48.475029,
    "lon": -121.057084
  },
  {
    "lat": 48.47515,
    "lon": -121.056751
  },
  {
    "lat": 48.476078,
    "lon": -121.056615
  },
  {
    "lat": 48.476195,
    "lon": -121.056739
  },
  {
    "lat": 48.47642,
    "lon": -121.056543
  },
  {
    "lat": 48.477026,
    "lon": -121.057192
  },
  {
    "lat": 48.477258,
    "lon": -121.05708
  },
  {
    "lat": 48.477706,
    "lon": -121.056459
  },
  {
    "lat": 48.47794,
    "lon": -121.055812
  },
  {
    "lat": 48.478315,
    "lon": -121.055812
  },
  {
    "lat": 48.479961,
    "lon": -121.053974
  },
  {
    "lat": 48.480121,
    "lon": -121.0535
  },
  {
    "lat": 48.480729,
    "lon": -121.052746
  },
  {
    "lat": 48.480874,
    "lon": -121.052839
  },
  {
    "lat": 48.481437,
    "lon": -121.052572
  },
  {
    "lat": 48.481762,
    "lon": -121.051804
  },
  {
    "lat": 48.482362,
    "lon": -121.051255
  },
  {
    "lat": 48.482377,
    "lon": -121.05092
  },
  {
    "lat": 48.482703,
    "lon": -121.050556
  },
  {
    "lat": 48.482708,
    "lon": -121.049753
  },
  {
    "lat": 48.483021,
    "lon": -121.049198
  },
  {
    "lat": 48.483176,
    "lon": -121.048462
  },
  {
    "lat": 48.483238,
    "lon": -121.048569
  },
  {
    "lat": 48.483435,
    "lon": -121.048433
  },
  {
    "lat": 48.483833,
    "lon": -121.04788
  },
  {
    "lat": 48.484111,
    "lon": -121.047772
  },
  {
    "lat": 48.48441,
    "lon": -121.046909
  },
  {
    "lat": 48.484868,
    "lon": -121.046581
  },
  {
    "lat": 48.485047,
    "lon": -121.046027
  },
  {
    "lat": 48.48525,
    "lon": -121.046002
  },
  {
    "lat": 48.485365,
    "lon": -121.045285
  },
  {
    "lat": 48.4886,
    "lon": -121.042156
  },
  {
    "lat": 48.489635,
    "lon": -121.040529
  },
  {
    "lat": 48.48985,
    "lon": -121.039505
  },
  {
    "lat": 48.489732,
    "lon": -121.038806
  },
  {
    "lat": 48.489893,
    "lon": -121.038366
  },
  {
    "lat": 48.490451,
    "lon": -121.038256
  },
  {
    "lat": 48.491089,
    "lon": -121.038549
  },
  {
    "lat": 48.491352,
    "lon": -121.038347
  },
  {
    "lat": 48.491687,
    "lon": -121.038357
  },
  {
    "lat": 48.492915,
    "lon": -121.036736
  },
  {
    "lat": 48.493671,
    "lon": -121.036553
  },
  {
    "lat": 48.494789,
    "lon": -121.03595
  },
  {
    "lat": 48.48525,
    "lon": -121.046002
  },
  {
    "lat": 48.485425,
    "lon": -121.04663
  },
  {
    "lat": 48.484991,
    "lon": -121.046463
  },
  {
    "lat": 48.471872,
    "lon": -121.046466
  },
  {
    "lat": 48.471514,
    "lon": -121.047173
  },
  {
    "lat": 48.471529,
    "lon": -121.04791
  },
  {
    "lat": 48.471325,
    "lon": -121.048292
  },
  {
    "lat": 48.471487,
    "lon": -121.04854
  },
  {
    "lat": 48.471168,
    "lon": -121.049168
  },
  {
    "lat": 48.47082,
    "lon": -121.049343
  },
  {
    "lat": 48.471009,
    "lon": -121.049575
  },
  {
    "lat": 48.470895,
    "lon": -121.049908
  },
  {
    "lat": 48.471464,
    "lon": -121.050101
  },
  {
    "lat": 48.471966,
    "lon": -121.051255
  },
  {
    "lat": 48.471713,
    "lon": -121.051289
  },
  {
    "lat": 48.47149,
    "lon": -121.051076
  },
  {
    "lat": 48.471554,
    "lon": -121.05136
  },
  {
    "lat": 48.471406,
    "lon": -121.051216
  },
  {
    "lat": 48.471366,
    "lon": -121.051391
  },
  {
    "lat": 48.470773,
    "lon": -121.051587
  },
  {
    "lat": 48.470719,
    "lon": -121.051992
  },
  {
    "lat": 48.470134,
    "lon": -121.052055
  },
  {
    "lat": 48.468004,
    "lon": -121.058718
  },
  {
    "lat": 48.467596,
    "lon": -121.059048
  },
  {
    "lat": 48.467804,
    "lon": -121.059468
  },
  {
    "lat": 48.468264,
    "lon": -121.059438
  },
  {
    "lat": 48.468505,
    "lon": -121.059081
  },
  {
    "lat": 48.468656,
    "lon": -121.059442
  },
  {
    "lat": 48.469138,
    "lon": -121.059325
  },
  {
    "lat": 48.470389,
    "lon": -121.06032
  },
  {
    "lat": 48.471038,
    "lon": -121.060486
  },
  {
    "lat": 48.471601,
    "lon": -121.061468
  },
  {
    "lat": 48.471966,
    "lon": -121.061643
  },
  {
    "lat": 48.472076,
    "lon": -121.061887
  },
  {
    "lat": 48.473565,
    "lon": -121.06216
  },
  {
    "lat": 48.473881,
    "lon": -121.062635
  },
  {
    "lat": 48.47418,
    "lon": -121.06259
  },
  {
    "lat": 48.474401,
    "lon": -121.063042
  },
  {
    "lat": 48.475067,
    "lon": -121.063365
  },
  {
    "lat": 48.475654,
    "lon": -121.06416
  },
  {
    "lat": 48.476724,
    "lon": -121.064728
  },
  {
    "lat": 48.477516,
    "lon": -121.065563
  },
  {
    "lat": 48.477952,
    "lon": -121.06573
  },
  {
    "lat": 48.477481,
    "lon": -121.065832
  },
  {
    "lat": 48.476155,
    "lon": -121.065169
  },
  {
    "lat": 48.477207,
    "lon": -121.066383
  },
  {
    "lat": 48.47804,
    "lon": -121.066733
  },
  {
    "lat": 48.477415,
    "lon": -121.066851
  },
  {
    "lat": 48.476682,
    "lon": -121.066544
  },
  {
    "lat": 48.477258,
    "lon": -121.067207
  },
  {
    "lat": 48.477998,
    "lon": -121.067401
  },
  {
    "lat": 48.477286,
    "lon": -121.0676
  },
  {
    "lat": 48.477618,
    "lon": -121.067822
  },
  {
    "lat": 48.478173,
    "lon": -121.067908
  },
  {
    "lat": 48.477826,
    "lon": -121.067972
  },
  {
    "lat": 48.478357,
    "lon": -121.068037
  },
  {
    "lat": 48.479028,
    "lon": -121.06837
  },
  {
    "lat": 48.47843,
    "lon": -121.068403
  },
  {
    "lat": 48.479028,
    "lon": -121.06863
  },
  {
    "lat": 48.47841,
    "lon": -121.068743
  },
  {
    "lat": 48.479012,
    "lon": -121.068988
  },
  {
    "lat": 48.47786,
    "lon": -121.069269
  },
  {
    "lat": 48.477575,
    "lon": -121.069178
  },
  {
    "lat": 48.478066,
    "lon": -121.069658
  },
  {
    "lat": 48.478219,
    "lon": -121.069632
  },
  {
    "lat": 48.478235,
    "lon": -121.069808
  },
  {
    "lat": 48.478076,
    "lon": -121.069908
  },
  {
    "lat": 48.477679,
    "lon": -121.069691
  },
  {
    "lat": 48.477574,
    "lon": -121.06984
  },
  {
    "lat": 48.477345,
    "lon": -121.069769
  },
  {
    "lat": 48.477485,
    "lon": -121.070064
  },
  {
    "lat": 48.477722,
    "lon": -121.070007
  },
  {
    "lat": 48.478085,
    "lon": -121.070378
  },
  {
    "lat": 48.477862,
    "lon": -121.070292
  },
  {
    "lat": 48.477528,
    "lon": -121.070465
  },
  {
    "lat": 48.477945,
    "lon": -121.070597
  },
  {
    "lat": 48.47867,
    "lon": -121.07117
  },
  {
    "lat": 48.478008,
    "lon": -121.070972
  },
  {
    "lat": 48.477578,
    "lon": -121.071085
  },
  {
    "lat": 48.477242,
    "lon": -121.070845
  },
  {
    "lat": 48.477432,
    "lon": -121.071215
  },
  {
    "lat": 48.477942,
    "lon": -121.071305
  },
  {
    "lat": 48.478407,
    "lon": -121.071751
  },
  {
    "lat": 48.477873,
    "lon": -121.071566
  },
  {
    "lat": 48.477696,
    "lon": -121.071889
  },
  {
    "lat": 48.476914,
    "lon": -121.07139
  },
  {
    "lat": 48.477229,
    "lon": -121.071976
  },
  {
    "lat": 48.476585,
    "lon": -121.071572
  },
  {
    "lat": 48.477541,
    "lon": -121.072632
  },
  {
    "lat": 48.476366,
    "lon": -121.071824
  },
  {
    "lat": 48.477707,
    "lon": -121.073449
  },
  {
    "lat": 48.476878,
    "lon": -121.072842
  },
  {
    "lat": 48.475602,
    "lon": -121.072654
  },
  {
    "lat": 48.475925,
    "lon": -121.072986
  },
  {
    "lat": 48.476655,
    "lon": -121.073262
  },
  {
    "lat": 48.476931,
    "lon": -121.073608
  },
  {
    "lat": 48.476236,
    "lon": -121.073284
  },
  {
    "lat": 48.475211,
    "lon": -121.073538
  },
  {
    "lat": 48.475789,
    "lon": -121.073809
  },
  {
    "lat": 48.475206,
    "lon": -121.074075
  },
  {
    "lat": 48.474959,
    "lon": -121.073955
  },
  {
    "lat": 48.47523,
    "lon": -121.074345
  },
  {
    "lat": 48.475819,
    "lon": -121.074324
  },
  {
    "lat": 48.47598,
    "lon": -121.075098
  },
  {
    "lat": 48.475661,
    "lon": -121.0751
  },
  {
    "lat": 48.475501,
    "lon": -121.074877
  },
  {
    "lat": 48.475324,
    "lon": -121.075475
  },
  {
    "lat": 48.47536,
    "lon": -121.075287
  },
  {
    "lat": 48.475126,
    "lon": -121.075273
  },
  {
    "lat": 48.474766,
    "lon": -121.074662
  },
  {
    "lat": 48.480553,
    "lon": -121.07979
  },
  {
    "lat": 48.481562,
    "lon": -121.079381
  },
  {
    "lat": 48.482089,
    "lon": -121.079357
  },
  {
    "lat": 48.483268,
    "lon": -121.079565
  },
  {
    "lat": 48.48431,
    "lon": -121.080062
  },
  {
    "lat": 48.484901,
    "lon": -121.080126
  },
  {
    "lat": 48.485311,
    "lon": -121.079687
  },
  {
    "lat": 48.48525,
    "lon": -121.079435
  },
  {
    "lat": 48.484947,
    "lon": -121.079326
  },
  {
    "lat": 48.48507,
    "lon": -121.078806
  },
  {
    "lat": 48.484227,
    "lon": -121.078535
  },
  {
    "lat": 48.484793,
    "lon": -121.077574
  },
  {
    "lat": 48.484264,
    "lon": -121.077402
  },
  {
    "lat": 48.4841,
    "lon": -121.077167
  },
  {
    "lat": 48.484789,
    "lon": -121.076105
  },
  {
    "lat": 48.485696,
    "lon": -121.075097
  },
  {
    "lat": 48.48582,
    "lon": -121.073676
  },
  {
    "lat": 48.486698,
    "lon": -121.071472
  },
  {
    "lat": 48.487318,
    "lon": -121.071365
  },
  {
    "lat": 48.488126,
    "lon": -121.070871
  },
  {
    "lat": 48.488835,
    "lon": -121.07103
  },
  {
    "lat": 48.489214,
    "lon": -121.070818
  },
  {
    "lat": 48.489684,
    "lon": -121.071073
  },
  {
    "lat": 48.490388,
    "lon": -121.070317
  },
  {
    "lat": 48.490802,
    "lon": -121.07023
  },
  {
    "lat": 48.490904,
    "lon": -121.069984
  },
  {
    "lat": 48.491394,
    "lon": -121.069829
  },
  {
    "lat": 48.491741,
    "lon": -121.070015
  },
  {
    "lat": 48.491996,
    "lon": -121.069464
  },
  {
    "lat": 48.492211,
    "lon": -121.069396
  },
  {
    "lat": 48.49219,
    "lon": -121.069073
  },
  {
    "lat": 48.492482,
    "lon": -121.069095
  },
  {
    "lat": 48.492037,
    "lon": -121.067547
  },
  {
    "lat": 48.492115,
    "lon": -121.067142
  },
  {
    "lat": 48.492379,
    "lon": -121.066911
  },
  {
    "lat": 48.492643,
    "lon": -121.0671
  },
  {
    "lat": 48.493059,
    "lon": -121.066908
  },
  {
    "lat": 48.492906,
    "lon": -121.066576
  },
  {
    "lat": 48.49299,
    "lon": -121.066321
  },
  {
    "lat": 48.493626,
    "lon": -121.066337
  },
  {
    "lat": 48.494171,
    "lon": -121.064998
  },
  {
    "lat": 48.495016,
    "lon": -121.065351
  },
  {
    "lat": 48.495304,
    "lon": -121.064707
  },
  {
    "lat": 48.496116,
    "lon": -121.06395
  },
  {
    "lat": 48.496991,
    "lon": -121.064406
  },
  {
    "lat": 48.49703,
    "lon": -121.063593
  },
  {
    "lat": 48.49721,
    "lon": -121.063419
  },
  {
    "lat": 48.496965,
    "lon": -121.063074
  },
  {
    "lat": 48.497231,
    "lon": -121.062724
  },
  {
    "lat": 48.497594,
    "lon": -121.062669
  },
  {
    "lat": 48.498314,
    "lon": -121.062903
  },
  {
    "lat": 48.498319,
    "lon": -121.0622
  },
  {
    "lat": 48.498639,
    "lon": -121.061621
  },
  {
    "lat": 48.498983,
    "lon": -121.059919
  },
  {
    "lat": 48.499401,
    "lon": -121.059425
  },
  {
    "lat": 48.500126,
    "lon": -121.060462
  },
  {
    "lat": 48.500723,
    "lon": -121.060872
  },
  {
    "lat": 48.501308,
    "lon": -121.061858
  },
  {
    "lat": 48.501358,
    "lon": -121.062829
  },
  {
    "lat": 48.501544,
    "lon": -121.063331
  },
  {
    "lat": 48.495283,
    "lon": -121.064759
  },
  {
    "lat": 48.49479,
    "lon": -121.063542
  },
  {
    "lat": 48.477295,
    "lon": -121.057192
  },
  {
    "lat": 48.477092,
    "lon": -121.056532
  }
]